module/__init__.py
module/kuramoto.py
module/plotting.py
oscillators_pkg-0.1.dist-info/METADATA
oscillators_pkg-0.1.dist-info/WHEEL
oscillators_pkg-0.1.dist-info/top_level.txt
oscillators_pkg-0.1.dist-info/RECORD
