Metadata-Version: 2.1
Name: oscillators-pkg
Version: 0.1
Summary: A package for simulating oscillators
Home-page: https://github.com/your_username/oscillators_pkg
Author: Your Name
Author-email: your.email@example.com
Classifier: Programming Language :: Python :: 3
Classifier: License :: OSI Approved :: MIT License
Classifier: Operating System :: OS Independent
Requires-Python: >=3.6
Requires-Dist: numpy
Requires-Dist: numba
Requires-Dist: matplotlib
